LICENSE
MANIFEST.in
README.rst
setup.cfg
setup.py
tracetools/__init__.py
tracetools/tests.py
tracetools/tracetools.py
tracetools.egg-info/PKG-INFO
tracetools.egg-info/SOURCES.txt
tracetools.egg-info/dependency_links.txt
tracetools.egg-info/top_level.txt
tracetools.egg-info/zip-safe