Metadata-Version: 1.1
Name: tracetools
Version: 1.24
Summary: Trace toolkit to print formatted traces of binary data
Home-page: https://github.com/timgabets/tracetools
Author: Tim Gabets
Author-email: tim@gabets.ru
License: LGPLv2
Keywords: trace hex
Platform: UNKNOWN
Classifier: License :: OSI Approved :: GNU Lesser General Public License v2 (LGPLv2)
Classifier: Operating System :: OS Independent
Classifier: Programming Language :: Python :: 2
Classifier: Programming Language :: Python :: 2.7
Classifier: Programming Language :: Python :: 3
Classifier: Programming Language :: Python :: 3.3
Classifier: Programming Language :: Python :: 3.4
Classifier: Programming Language :: Python :: 3.5
Classifier: Topic :: Communications
Classifier: Intended Audience :: Developers
